llm_embedding_eval.py
llm_embedding_eval-0.1.dist-info/LICENSE
llm_embedding_eval-0.1.dist-info/METADATA
llm_embedding_eval-0.1.dist-info/WHEEL
llm_embedding_eval-0.1.dist-info/entry_points.txt
llm_embedding_eval-0.1.dist-info/top_level.txt
llm_embedding_eval-0.1.dist-info/RECORD
