Metadata-Version: 2.2
Name: llm-embedding-eval
Version: 0.1
Summary: LLM plugin for embedding evaluation with semantic scoring
Author: Ajay Arunachalam
License: Apache-2.0
Project-URL: Homepage, https://github.com/ajayarunachalam/llm-embedding-eval
Project-URL: Issues, https://github.com/ajayarunachalam/llm-embedding-eval/issues
Classifier: License :: OSI Approved :: Apache Software License
License-File: LICENSE
Requires-Dist: llm>=0.9
Requires-Dist: numpy>=1.20
Requires-Dist: torch>=1.9
Requires-Dist: transformers>=4.0
Requires-Dist: accelerate>=0.20
Provides-Extra: test
Requires-Dist: pytest; extra == "test"
